shore/__init__.py
shore/calculation.py
shore/gview.py
shore/input_manager.py
shore/jobcreator.py
shore/remote.py
shore/results.py
shore/workflow_graph.py
shore_pkg_geonda-0.1.4.dist-info/LICENSE
shore_pkg_geonda-0.1.4.dist-info/METADATA
shore_pkg_geonda-0.1.4.dist-info/WHEEL
shore_pkg_geonda-0.1.4.dist-info/top_level.txt
shore_pkg_geonda-0.1.4.dist-info/RECORD
