Metadata-Version: 2.1
Name: shore-pkg-geonda
Version: 0.1.4
Summary: python wrapper for OCEAN-FEFF
Home-page: https://github.com/geonda/shore
Author: Andrey Geondzhian
Author-email: a.geondzhian@gmail.com
License-File: LICENSE
Requires-Dist: ase==3.23.0
Requires-Dist: ipython==8.12.3
Requires-Dist: networkx==3.4.1
Requires-Dist: numpy<2.0.0
Requires-Dist: paramiko==3.5.0
Requires-Dist: plotly==5.24.1
Requires-Dist: seaborn==0.13.2
Requires-Dist: setuptools==75.3.0
Requires-Dist: spglib==2.5.0
Requires-Dist: tqdm==4.66.6
Requires-Dist: nbformat>=4.2.0
